mwparserfromhell-stubs/__init__.pyi
mwparserfromhell-stubs/definitions.pyi
mwparserfromhell-stubs/nodes/__init__.pyi
mwparserfromhell-stubs/nodes/_base.pyi
mwparserfromhell-stubs/nodes/argument.pyi
mwparserfromhell-stubs/nodes/comment.pyi
mwparserfromhell-stubs/nodes/external_link.pyi
mwparserfromhell-stubs/nodes/extras/__init__.pyi
mwparserfromhell-stubs/nodes/extras/attribute.pyi
mwparserfromhell-stubs/nodes/extras/parameter.pyi
mwparserfromhell-stubs/nodes/heading.pyi
mwparserfromhell-stubs/nodes/html_entity.pyi
mwparserfromhell-stubs/nodes/tag.pyi
mwparserfromhell-stubs/nodes/template.pyi
mwparserfromhell-stubs/nodes/text.pyi
mwparserfromhell-stubs/nodes/wikilink.pyi
mwparserfromhell-stubs/parser/__init__.pyi
mwparserfromhell-stubs/parser/builder.pyi
mwparserfromhell-stubs/parser/contexts.pyi
mwparserfromhell-stubs/parser/errors.pyi
mwparserfromhell-stubs/parser/tokenizer.pyi
mwparserfromhell-stubs/parser/tokens.pyi
mwparserfromhell-stubs/smart_list/__init__.pyi
mwparserfromhell-stubs/smart_list/list_proxy.pyi
mwparserfromhell-stubs/smart_list/smart_list.pyi
mwparserfromhell-stubs/smart_list/utils.pyi
mwparserfromhell-stubs/string_mixin.pyi
mwparserfromhell-stubs/utils.pyi
mwparserfromhell-stubs/wikicode.pyi
mwparserfromhell_stubs-0.7.2.250702.dist-info/LICENSE
mwparserfromhell_stubs-0.7.2.250702.dist-info/METADATA
mwparserfromhell_stubs-0.7.2.250702.dist-info/WHEEL
mwparserfromhell_stubs-0.7.2.250702.dist-info/RECORD
