Metadata-Version: 2.3
Name: mwparserfromhell-stubs
Version: 0.7.2.250702
Summary: Type annotations for mwparserfromhell
License: MIT
Author: JJMC89
Requires-Python: >=3.9
Classifier: Intended Audience :: Developers
Classifier: License :: OSI Approved :: MIT License
Classifier: Programming Language :: Python :: 3
Classifier: Programming Language :: Python :: 3.9
Classifier: Programming Language :: Python :: 3.10
Classifier: Programming Language :: Python :: 3.11
Classifier: Programming Language :: Python :: 3.12
Classifier: Programming Language :: Python :: 3.13
Classifier: Typing :: Stubs Only
Requires-Dist: typing-extensions (>=4.0.0)
Project-URL: Repository, https://github.com/JJMC89/mwparserfromhell-stubs
